holdings_maintenance/__init__.py
holdings_maintenance/pds3/copy_all_except_metadata.sh
holdings_maintenance/pds3/copy_documents.sh
holdings_maintenance/pds3/copy_shelves.sh
holdings_maintenance/pds3/create_fake_volumes_for_metadata.sh
holdings_maintenance/pds3/crlf.py
holdings_maintenance/pds3/pdsarchives.py
holdings_maintenance/pds3/pdschecksums.py
holdings_maintenance/pds3/pdsdata-sync-volset-metadata.sh
holdings_maintenance/pds3/pdsdata-sync-volset-previews.sh
holdings_maintenance/pds3/pdsdata-sync-volset.sh
holdings_maintenance/pds3/pdsdata-sync-volume-metadata.sh
holdings_maintenance/pds3/pdsdata-sync-volume.sh
holdings_maintenance/pds3/pdsdata-sync.sh
holdings_maintenance/pds3/pdsdependency.py
holdings_maintenance/pds3/pdsindexshelf.py
holdings_maintenance/pds3/pdsinfoshelf.py
holdings_maintenance/pds3/pdslinkshelf.py
holdings_maintenance/pds3/re-validate.py
holdings_maintenance/pds3/setup_new_holdings.sh
holdings_maintenance/pds3/shelf-consistency-check.py
holdings_maintenance/pds3/update_holdings_for_new_metadata.sh
pdsfile/__init__.py
pdsfile/_version.py
pdsfile/pdscache.py
pdsfile/pdsfile.py
pdsfile/pdsfile_test_helper.py
pdsfile/pdsviewable.py
pdsfile/preload_and_cache.py
pdsfile/pds3file/__init__.py
pdsfile/pds3file/rules/ASTROM_xxxx.py
pdsfile/pds3file/rules/COCIRS_xxxx.py
pdsfile/pds3file/rules/COISS_xxxx.py
pdsfile/pds3file/rules/CORSS_8xxx.py
pdsfile/pds3file/rules/COSP_xxxx.py
pdsfile/pds3file/rules/COUVIS_0xxx.py
pdsfile/pds3file/rules/COUVIS_8xxx.py
pdsfile/pds3file/rules/COVIMS_0xxx.py
pdsfile/pds3file/rules/COVIMS_8xxx.py
pdsfile/pds3file/rules/EBROCC_xxxx.py
pdsfile/pds3file/rules/GO_0xxx.py
pdsfile/pds3file/rules/HSTxx_xxxx.py
pdsfile/pds3file/rules/JNOJIR_xxxx.py
pdsfile/pds3file/rules/JNOJNC_xxxx.py
pdsfile/pds3file/rules/JNOSP_xxxx.py
pdsfile/pds3file/rules/NHSP_xxxx.py
pdsfile/pds3file/rules/NHxxxx_xxxx.py
pdsfile/pds3file/rules/RES_xxxx.py
pdsfile/pds3file/rules/RPX_xxxx.py
pdsfile/pds3file/rules/VGIRIS_xxxx.py
rms_pdsfile-0.0.17.dist-info/licenses/LICENSE
rms_pdsfile-0.0.17.dist-info/METADATA
rms_pdsfile-0.0.17.dist-info/WHEEL
rms_pdsfile-0.0.17.dist-info/entry_points.txt
rms_pdsfile-0.0.17.dist-info/top_level.txt
rms_pdsfile-0.0.17.dist-info/RECORD
