Metadata-Version: 2.4
Name: rms-pdsfile
Version: 0.0.17
Summary: pdsfile
Maintainer-email: "Robert S. French" <rfrench@seti.org>
License: Apache-2.0
Project-URL: Homepage, https://github.com/SETI/rms-pdsfile
Project-URL: Repository, https://github.com/SETI/rms-pdsfile
Project-URL: Source, https://github.com/SETI/rms-pdsfile
Project-URL: Issues, https://github.com/SETI/rms-pdsfile/issues
Keywords: pdsfile
Classifier: Development Status :: 5 - Production/Stable
Classifier: Natural Language :: English
Classifier: Topic :: Scientific/Engineering
Classifier: Topic :: Scientific/Engineering :: Astronomy
Classifier: Topic :: Software Development :: Libraries :: Python Modules
Classifier: Topic :: Utilities
Classifier: License :: OSI Approved :: Apache Software License
Classifier: Programming Language :: Python :: 3.10
Classifier: Programming Language :: Python :: 3.11
Classifier: Programming Language :: Python :: 3.12
Classifier: Programming Language :: Python :: 3.13
Classifier: Operating System :: MacOS :: MacOS X
Classifier: Operating System :: POSIX :: Linux
Classifier: Operating System :: Microsoft :: Windows
Requires-Python: >=3.10
License-File: LICENSE
Requires-Dist: numpy
Requires-Dist: pillow
Requires-Dist: pyparsing
Requires-Dist: pytest
Requires-Dist: rms-pdslogger>=3.1.1
Requires-Dist: rms-pdstable
Requires-Dist: rms-translator
Requires-Dist: rms-textkernel
Dynamic: license-file
